<V6 xmlns:ns0="QyrG" xmlns:ns1="ZlD" id="1" m1="-P5387Y7498M6585DT2749H831M4603S">
	<ns0:Y9 id="4" a14="-P324Y3786M111DT873H4297M8195S" i14="false" h6="true">
		<ns0:Z8 id="42" j22="~` -3" b9="] x7sc{">
			<ns1:I4 id="60">
				<ns1:E18 id="633">
					<ns1:L2 id="831" x6="FKoqfrv. cNeM" w6="true" l14="P8238Y8559M8204DT4108H855M6238S">t\w2d</ns1:L2>
					v1  2
				</ns1:E18>
				-P5524Y2061M7991DT5846H2226M33S
			</ns1:I4>
			<ns0:T18 id="255" k1="-1333090803">-P5889Y6178M77DT3754H2812M3813S</ns0:T18>
			<ns0:W4 id="498" k9="381722480" b10="CP   7dg    $y">-28883.6603</ns0:W4>
			<ns0:H15 id="740" c5="205928058" m7="-P5835Y850M5861DT987H2678M2344S" b10="R7x wMn{BX;OQ pLPCr1F" p5="WPM">true</ns0:H15>
			<ns0:W24 id="929" g7="y  =  ^k7[mte_7^" j4="rtk">SZh9tmZe;9 ~OR</ns0:W24>
			false
		</ns0:Z8>
		<ns0:Z6 id="48" n3="-81709.8691" i3="150146861">
			<ns1:L19 id="198" m16="-4722.3379">
				<ns1:F6 id="223" h14="-P2272Y2381M6373DT1589H6982M4880S" g1="f1P[tN|aCan[ cg 1i" i10="true">
					<ns0:X23 id="520" q7="454657798">
						<ns0:H21 id="977" j23="534843731">-1288735059</ns0:H21>
						X18
					</ns0:X23>
					<ns0:X5 id="994" t4="FSv_i .!} N" a8="P659Y5221M8473DT9916H2552M4656S" m5="-403345200" q4="P9206Y9293M7701DT10H7259M8563S">false</ns0:X5>
					-974652858
				</ns1:F6>
				<ns0:V17 id="726" i7="*[nkY7" j11="P450Y5087M9437DT5772H5681M5530S" l1="false" w6="true">W_? , m</ns0:V17>
				-P2303Y9096M3851DT5728H5922M3718S
			</ns1:L19>
			<ns0:A27 id="247" x4="82810.4183" k9="-1309821023">G]G\Ruj *6DA *u`</ns0:A27>
			-53240.7242
		</ns0:Z6>
		<ns0:W24 id="58" g7="PpA74O.6b F6#1hF 2" j4="JAC wv%1+">
			<ns0:Y20 id="106" s3="P7028Y1629M2850DT9043H7814M8752S">
				<ns0:L33 id="109" c10="Q4FLLeM  Ir[] e" x9="n ZL2IC">pn#;%]vo5d3,: Oe ~L</ns0:L33>
				<ns0:C33 id="717" j2="-82479.5885" a5="-1433950416">P6377Y2606M3987DT1435H9910M7200S</ns0:C33>
				P5422Y3127M4426DT1262H7979M5616S
			</ns0:Y20>
			<ns0:S3 id="363" y9="AZ  b99   Jvp.">x*;n</ns0:S3>
			<ns1:W39 id="504" j6="7`.ua rm| w5$M! O">-P3907Y4963M5604DT8354H159M4590S</ns1:W39>
			<ns0:X27 id="968" i17="E|JMj|7u I#M[~" d5="448823820">-1385285472</ns0:X27>
			]
		</ns0:W24>
		<ns0:C11 id="116" u5="3Zpv~OG;c[, B F $ .1" x5="-1514329950" l2="1632904481">
			<ns0:H10 id="252" c5="-1083425852">
				<ns0:E21 id="731" q7="1602381379" e7="true" d3="-1636054594" i16="-2069348138">false</ns0:E21>
				true
			</ns0:H10>
			1812108885
		</ns0:C11>
		<ns0:O2 id="274" y11="18849163" j11="-P9123Y8635M2667DT5408H2441M6943S" a11="false">-76.9932</ns0:O2>
		21822.6196
	</ns0:Y9>
	<W7 id="5" i11="58614.6331" y13="98697.4652" c7="?">
		<Z2 id="56" q10="-P7870Y3206M7864DT2372H9851M114S" m4="17Xpch">
			<Y21 id="100" l16="false">
				<D1 id="190" y8="33021.5162" y18="23755.4450" u11="=" r7="45555.2948">N4)|</D1>
				<ns0:O12 id="203" k18="false" a1="false" q3="G@5[gB" j6="IaP,gc8!5MCg|1">
					<ns0:B9 id="232" r4="-14480.6443" i3="-1615823538" l17="anVRk8c" k4="-1048794306">
						<ns1:P34 id="1000" n4="!_MidV?[DayRPr9{j">1832055055</ns1:P34>
						-35635.4944
					</ns0:B9>
					<ns1:F20 id="318" j14="-3325.3924" y11="-1985048481" r11="true" f17="19149.4230">
						<ns0:N1 id="562" u7="true">
							<ns0:V23 id="854" h8="P816Y2765M8545DT3775H6711M2699S" j11="-P19Y106M2091DT5562H6671M4991S">z^R</ns0:V23>
							P9459Y5374M61DT4169H7747M9555S
						</ns0:N1>
						u; i L?uB #: y
					</ns1:F20>
					P1482Y5945M9602DT8173H4380M9635S
				</ns0:O12>
				<ns1:L21 id="426">true</ns1:L21>
				8747.2000
			</Y21>
			<R11 id="103">
				<Y20 id="118" s3="P5949Y8471M4535DT972H3159M9935S">
					<ns1:O9 id="356">-P822Y2511M7375DT650H9585M6228S</ns1:O9>
					-P334Y2609M2246DT1054H1967M2639S
				</Y20>
				<L8 id="408" d5="1212164386" i14="true">
					<A20 id="556">
						<D9 id="856" z14="J%w q fS">590052589</D9>
						64468.3321
					</A20>
					-932545259
				</L8>
				@L VsTY Z`Vdzu!
			</R11>
			<Z4 id="169" q16="u %!" k17="7941.2697" f19="0Ujo 1+Q`r Ji">
				<ns1:N4 id="173" u7="true" b14="o 1u" y16="false">
					<ns1:V16 id="266" j22="I)\!0J3B" k5="true" y3="P7225Y8134M7717DT8865H3085M3167S">
						<ns1:G9 id="515">
							<ns0:Z3 id="664" w1="P3822Y3654M1663DT3092H9342M2770S">true</ns0:Z3>
							P8216Y1188M6700DT6329H365M9268S
						</ns1:G9>
						<ns1:N1 id="925" u7="true">P2449Y4186M4405DT7500H2235M473S</ns1:N1>
						false
					</ns1:V16>
					<ns1:Y7 id="425" m12="uAnkmBcslf  Q$?">
						<ns0:H4 id="428">P1665Y6872M3883DT3000H4812M285S</ns0:H4>
						1851635328
					</ns1:Y7>
					pAsK  E :r
				</ns1:N4>
				_ G ssIo
			</Z4>
			<T12 id="481" a5="-987514264">1923463467</T12>
			<ns0:P15 id="776" r7="50287.3888" o1="true">P391Y5421M8226DT2182H6876M2184S</ns0:P15>
			-267786879
		</Z2>
		<ns0:H4 id="156">
			<L12 id="589" f19="+dxNm8R+ LEP" q4="-P7146Y3861M713DT9026H5642M9801S" i8="9D@Q {cmyKSe2tnbC+">P4995Y2449M7162DT855H7441M1864S</L12>
			<F26 id="938">-1592009080</F26>
			-P7808Y1533M4064DT1334H1486M9004S
		</ns0:H4>
		<ns0:F18 id="183" p5="Kv}o{*XL" j1="J N 4SQ d3t?">
			<R12 id="609" h4="69792.2381">Nz-K; ut=y 6v6EYFw</R12>
			94034.3522
		</ns0:F18>
		7dYseDSx=Q
	</W7>
	<I6 id="38">
		<K10 id="53" n8="-1427374949" v4="V,TQi">
			<Y12 id="384">2 6Op b</Y12>
			false
		</K10>
		cduN  r ` IS
	</I6>
	<X21 id="283" j11="P291Y1595M1214DT4304H5368M6556S" p6="V!#h">
		<ns0:Q16 id="285" i11="25448.1448" f9="k? 2" y1="-P6017Y3985M5224DT9074H8111M2824S">
			<ns0:F31 id="341" g7="v5%!G.SN" t9="%">1314588485</ns0:F31>
			-P4987Y3323M8895DT2905H6289M6284S
		</ns0:Q16>
		false
	</X21>
	<Q34 id="505">-719019840</Q34>
	<Y20 id="754" s3="P2597Y70M5207DT3240H2447M4618S">P4814Y2022M3696DT7266H1846M8401S</Y20>
	<ns1:E22 id="841" a15="-95446.8574" o11="25602.5021" c9="-P8697Y1402M2184DT7213H4667M5153S" c8="-140399901">;JUt|4g d`M[]</ns1:E22>
	<P24 id="914" d11="-77784.9263">P1141Y7444M5107DT850H249M1376S</P24>
	-P2328Y7151M5257DT3889H4036M2930S
</V6>